pystaticconfig/__init__.py
pystaticconfig/pystaticconfig.py
pystaticconfig-0.0.2.dist-info/LICENSE
pystaticconfig-0.0.2.dist-info/METADATA
pystaticconfig-0.0.2.dist-info/WHEEL
pystaticconfig-0.0.2.dist-info/top_level.txt
pystaticconfig-0.0.2.dist-info/RECORD
