Metadata-Version: 2.1
Name: pystaticconfig
Version: 0.0.2
Summary: JSON config with static class in python
Home-page: https://github.com/IvanFoke/PyStaticConfig
Author: Ivan Chistiakov
License: UNKNOWN
Platform: UNKNOWN
Classifier: Programming Language :: Python :: 3
Classifier: License :: OSI Approved :: MIT License
Classifier: Operating System :: OS Independent
